setup.py
tidytex.py
tidytex.egg-info/PKG-INFO
tidytex.egg-info/SOURCES.txt
tidytex.egg-info/dependency_links.txt
tidytex.egg-info/entry_points.txt
tidytex.egg-info/requires.txt
tidytex.egg-info/top_level.txt