Metadata-Version: 1.1
Name: tidytex
Version: 0.1
Summary: Compile LaTeX with no auxiliary files
Home-page: https://github.com/ColCarroll/tidytex
Author: Colin Carroll
Author-email: UNKNOWN
License: GPLv3
Platform: UNKNOWN
Classifier: License :: OSI Approved :: GNU General Public License v3 (GPLv3)
Classifier: Environment :: Console
Classifier: Topic :: Text Processing :: Markup :: LaTeX
